MANIFEST.in
Readme.md
dev-requirements.frozen.txt
dev-requirements.txt
licence.txt
noxfile.py
requirements.frozen.txt
requirements.txt
setup.cfg
setup.py
pandas_ta_quant_plot/__init__.py
pandas_ta_quant_plot/plot_container.py
pandas_ta_quant_plot/plot_utils.py
pandas_ta_quant_plot/ta_plot_context.py
pandas_ta_quant_plot.egg-info/PKG-INFO
pandas_ta_quant_plot.egg-info/SOURCES.txt
pandas_ta_quant_plot.egg-info/dependency_links.txt
pandas_ta_quant_plot.egg-info/requires.txt
pandas_ta_quant_plot.egg-info/top_level.txt
pandas_ta_quant_plot/__pycache__/__init__.cpython-37.pyc
pandas_ta_quant_plot/__pycache__/__init__.cpython-38.pyc
pandas_ta_quant_plot/__pycache__/plot_container.cpython-37.pyc
pandas_ta_quant_plot/__pycache__/plot_container.cpython-38.pyc
pandas_ta_quant_plot/__pycache__/plot_utils.cpython-37.pyc
pandas_ta_quant_plot/__pycache__/plot_utils.cpython-38.pyc
pandas_ta_quant_plot/__pycache__/ta_plot_context.cpython-37.pyc
pandas_ta_quant_plot/__pycache__/ta_plot_context.cpython-38.pyc
pandas_ta_quant_plot/plots/__init__.py
pandas_ta_quant_plot/plots/histogram.py
pandas_ta_quant_plot/plots/__pycache__/__init__.cpython-37.pyc
pandas_ta_quant_plot/plots/__pycache__/__init__.cpython-38.pyc
pandas_ta_quant_plot/plots/__pycache__/histogram.cpython-37.pyc
pandas_ta_quant_plot/plots/__pycache__/histogram.cpython-38.pyc
pandas_ta_quant_plot/plotting_bak/__init__.py
pandas_ta_quant_plot/plotting_bak/bar.py
pandas_ta_quant_plot/plotting_bak/candlestick.py
pandas_ta_quant_plot/plotting_bak/line.py
pandas_ta_quant_plot/plotting_bak/matrix.py
pandas_ta_quant_plot/plotting_bak/obsolete.txt
pandas_ta_quant_plot/plotting_bak/plot.py
pandas_ta_quant_plot/plotting_bak/utils.py
pandas_ta_quant_plot/plotting_bak/__pycache__/__init__.cpython-38.pyc
pandas_ta_quant_plot/plotting_bak/__pycache__/bar.cpython-38.pyc
pandas_ta_quant_plot/plotting_bak/animations/__init__.py
pandas_ta_quant_plot/plotting_bak/animations/animate.py
pandas_ta_quant_plot/plotting_bak/animations/__pycache__/__init__.cpython-38.pyc
pandas_ta_quant_plot/plotting_bak/animations/__pycache__/animate.cpython-38.pyc
pandas_ta_quant_plot_test/__init__.py
pandas_ta_quant_plot_test/check_links.py
